fastapi_firebase/__init__.py
fastapi_firebase/app.py
fastapi_firebase/auth.py
fastapi_firebase/schemes.py
fastapi_firebase-0.3.1.dist-info/WHEEL
fastapi_firebase-0.3.1.dist-info/METADATA
fastapi_firebase-0.3.1.dist-info/RECORD
