Metadata-Version: 2.1
Name: fastapi-firebase
Version: 0.3.1
Summary: FastAPI integration with firebase
Author: Francisco Del Roio
Author-email: francipvb@hotmail.com
Requires-Python: >=3.8,<4.0
Classifier: Programming Language :: Python :: 3
Classifier: Programming Language :: Python :: 3.10
Classifier: Programming Language :: Python :: 3.8
Classifier: Programming Language :: Python :: 3.9
Requires-Dist: fastapi (>0.60.0)
Requires-Dist: firebase-admin (>=5.2.0,<6.0.0)
Requires-Dist: python-multipart (>=0.0.5,<0.0.6)
